django_tastypie_crust-0.2.dist-info/DESCRIPTION.rst
django_tastypie_crust-0.2.dist-info/METADATA
django_tastypie_crust-0.2.dist-info/RECORD
django_tastypie_crust-0.2.dist-info/WHEEL
django_tastypie_crust-0.2.dist-info/pydist.json
django_tastypie_crust-0.2.dist-info/top_level.txt
tastycrust/__init__.py
tastycrust/api.py
tastycrust/authentication.py
tastycrust/resources.py
tastycrust/utils.py
