Metadata-Version: 2.0
Name: django-tastypie-crust
Version: 0.2
Summary: Goodies for Tastypie.
Home-page: https://github.com/uranusjr/django-tastypie-crust
Author: Tzu-ping Chung
Author-email: uranusjr@gmail.com
License: BSD License
Platform: UNKNOWN
Classifier: Environment :: Web Environment
Classifier: Framework :: Django
Classifier: Intended Audience :: Developers
Classifier: License :: OSI Approved :: BSD License
Classifier: Operating System :: OS Independent
Classifier: Programming Language :: Python
Classifier: Topic :: Internet :: WWW/HTTP
Classifier: Topic :: Internet :: WWW/HTTP :: Dynamic Content
Requires-Dist: django-tastypie
